tooling/__init__.py
tooling/cli.py
tooling/tooling.py
tooling-0.1.0.dist-info/entry_points.txt
tooling-0.1.0.dist-info/LICENSE
tooling-0.1.0.dist-info/WHEEL
tooling-0.1.0.dist-info/METADATA
tooling-0.1.0.dist-info/RECORD
